{"60562":{"36461076":{"cust_id":293199,"position":39,"start_position":16,"interval":-1,"avg_lap_time":-1,"fastest_lap_time":763041,"fast_lap":20,"laps_completed":26,"points":0,"incidents":8,"pace_percent":2.49},"36704149":{"cust_id":293199,"position":17,"start_position":24,"interval":-1,"avg_lap_time":-1,"fastest_lap_time":1100108,"fast_lap":22,"laps_completed":24,"points":0,"incidents":4,"pace_percent":1.19},"36825338":{"cust_id":293199,"position":34,"start_position":28,"interval":-1,"avg_lap_time":-1,"fastest_lap_time":815035,"fast_lap":27,"laps_completed":32,"points":0,"incidents":10,"pace_percent":1.73},"36945507":{"cust_id":293199,"position":12,"start_position":19,"interval":-1,"avg_lap_time":-1,"fastest_lap_time":985905,"fast_lap":23,"laps_completed":28,"points":2,"incidents":3,"pace_percent":1.11},"37184224":{"cust_id":293199,"position":51,"start_position":40,"interval":-1,"avg_lap_time":-1,"fastest_lap_time":871154,"fast_lap":4,"laps_completed":4,"points":0,"incidents":0,"pace_percent":7.09},"37304093":{"cust_id":293199,"position":17,"start_position":18,"interval":-1,"avg_lap_time":-1,"fastest_lap_time":1192255,"fast_lap":21,"laps_completed":23,"points":0,"incidents":4,"pace_percent":1.18},"37423596":{"cust_id":293199,"position":57,"start_position":23,"interval":-1,"avg_lap_time":-1,"fastest_lap_time":833910,"fast_lap":10,"laps_completed":10,"points":0,"incidents":2,"pace_percent":1.63},"37545006":{"cust_id":293199,"position":58,"start_position":13,"interval":-1,"avg_lap_time":-1,"fastest_lap_time":908876,"fast_lap":2,"laps_completed":4,"points":0,"incidents":10,"pace_percent":4.41},"37663291":{"cust_id":293199,"position":7,"start_position":18,"interval":-1,"avg_lap_time":-1,"fastest_lap_time":747478,"fast_lap":14,"laps_completed":35,"points":12,"incidents":2,"pace_percent":1.11},"37782814":{"cust_id":293199,"position":53,"start_position":7,"interval":-1,"avg_lap_time":-1,"fastest_lap_time":1054631,"fast_lap":6,"laps_completed":6,"points":0,"incidents":15,"pace_percent":2.09}},"63157":{"37968066":{"cust_id":293199,"position":25,"start_position":17,"interval":-1,"avg_lap_time":-1,"fastest_lap_time":752648,"fast_lap":27,"laps_completed":35,"points":0,"incidents":9,"pace_percent":1.4},"38181439":{"cust_id":293199,"position":14,"start_position":18,"interval":-1,"avg_lap_time":-1,"fastest_lap_time":1097554,"fast_lap":24,"laps_completed":25,"points":0,"incidents":4,"pace_percent":0.85},"38397329":{"cust_id":293199,"position":45,"start_position":14,"interval":-1,"avg_lap_time":-1,"fastest_lap_time":981547,"fast_lap":8,"laps_completed":8,"points":0,"incidents":4,"pace_percent":2.3},"38710704":{"cust_id":293199,"position":17,"start_position":23,"interval":-1,"avg_lap_time":-1,"fastest_lap_time":905689,"fast_lap":24,"laps_completed":30,"points":0,"incidents":0,"pace_percent":1.61},"39022667":{"cust_id":293199,"position":25,"start_position":17,"interval":-1,"avg_lap_time":-1,"fastest_lap_time":743502,"fast_lap":25,"laps_completed":33,"points":0,"incidents":10,"pace_percent":1.48},"39125721":{"cust_id":293199,"position":9,"start_position":8,"interval":-1,"avg_lap_time":-1,"fastest_lap_time":1049351,"fast_lap":20,"laps_completed":25,"points":8,"incidents":17,"pace_percent":0.84}},"65438":{"39531390":{"cust_id":293199,"position":8,"start_position":9,"interval":-1,"avg_lap_time":-1,"fastest_lap_time":1115468,"fast_lap":20,"laps_completed":24,"points":10,"incidents":3,"pace_percent":0.45},"39860787":{"cust_id":293199,"position":36,"start_position":15,"interval":-1,"avg_lap_time":-1,"fastest_lap_time":1318577,"fast_lap":10,"laps_completed":11,"points":0,"incidents":12,"pace_percent":1.22},"40297163":{"cust_id":293199,"position":5,"start_position":8,"interval":-1,"avg_lap_time":-1,"fastest_lap_time":967310,"fast_lap":25,"laps_completed":28,"points":16,"incidents":8,"pace_percent":0.83},"40410730":{"cust_id":293199,"position":11,"start_position":11,"interval":-1,"avg_lap_time":-1,"fastest_lap_time":845522,"fast_lap":23,"laps_completed":28,"points":4,"incidents":10,"pace_percent":1.11},"40523272":{"cust_id":293199,"position":32,"start_position":18,"interval":-1,"avg_lap_time":-1,"fastest_lap_time":1116572,"fast_lap":18,"laps_completed":21,"points":0,"incidents":16,"pace_percent":1.23}},"67781":{"40792218":{"cust_id":293199,"position":19,"start_position":24,"interval":-1,"avg_lap_time":-1,"fastest_lap_time":983549,"fast_lap":16,"laps_completed":28,"points":0,"incidents":6,"pace_percent":0.94},"41422105":{"cust_id":293199,"position":4,"start_position":6,"interval":-1,"avg_lap_time":-1,"fastest_lap_time":1121151,"fast_lap":20,"laps_completed":24,"points":18,"incidents":4,"pace_percent":0.67},"41561656":{"cust_id":293199,"position":17,"start_position":25,"interval":-1,"avg_lap_time":-1,"fastest_lap_time":920636,"fast_lap":21,"laps_completed":30,"points":0,"incidents":10,"pace_percent":0.7},"41704730":{"cust_id":293199,"position":6,"start_position":9,"interval":-1,"avg_lap_time":-1,"fastest_lap_time":709825,"fast_lap":33,"laps_completed":38,"points":14,"incidents":0,"pace_percent":0.86},"41908727":{"cust_id":293199,"position":9,"start_position":13,"interval":-1,"avg_lap_time":-1,"fastest_lap_time":748647,"fast_lap":28,"laps_completed":36,"points":9,"incidents":0,"pace_percent":0.89},"42191961":{"cust_id":293199,"position":29,"start_position":7,"interval":-1,"avg_lap_time":-1,"fastest_lap_time":593116,"fast_lap":30,"laps_completed":43,"points":0,"incidents":17,"pace_percent":1.3},"42578537":{"cust_id":293199,"position":9,"start_position":15,"interval":-1,"avg_lap_time":-1,"fastest_lap_time":888358,"fast_lap":25,"laps_completed":30,"points":8,"incidents":2,"pace_percent":0.91}},"74865":{"43376961":{"cust_id":293199,"position":12,"start_position":17,"interval":-1,"avg_lap_time":-1,"fastest_lap_time":1182705,"fast_lap":18,"laps_completed":23,"points":2,"incidents":5,"pace_percent":0.65},"43765057":{"cust_id":293199,"position":35,"start_position":17,"interval":-1,"avg_lap_time":-1,"fastest_lap_time":1188300,"fast_lap":10,"laps_completed":10,"points":0,"incidents":2,"pace_percent":1.82},"43892971":{"cust_id":293199,"position":49,"start_position":24,"interval":-1,"avg_lap_time":-1,"fastest_lap_time":937123,"fast_lap":8,"laps_completed":11,"points":0,"incidents":13,"pace_percent":1.7},"44019536":{"cust_id":293199,"position":6,"start_position":6,"interval":-1,"avg_lap_time":-1,"fastest_lap_time":708461,"fast_lap":35,"laps_completed":38,"points":14,"incidents":1,"pace_percent":0.49},"44157605":{"cust_id":293199,"position":11,"start_position":10,"interval":-1,"avg_lap_time":-1,"fastest_lap_time":749363,"fast_lap":20,"laps_completed":36,"points":4,"incidents":1,"pace_percent":1.32},"44419401":{"cust_id":293199,"position":36,"start_position":17,"interval":-1,"avg_lap_time":-1,"fastest_lap_time":1066352,"fast_lap":13,"laps_completed":18,"points":0,"incidents":13,"pace_percent":1.16}},"78210":{"44990776":{"cust_id":293199,"position":31,"start_position":16,"interval":-1,"avg_lap_time":-1,"fastest_lap_time":978070,"fast_lap":22,"laps_completed":27,"points":0,"incidents":17,"pace_percent":1.16}}}