{"success":true,"session_info":{"subsession_id":51745857,"session_id":189796430,"simsession_number":-1,"simsession_type":4,"simsession_name":"QUALIFY","num_laps_for_qual_average":1,"num_laps_for_solo_average":1,"event_type":5,"event_type_name":"Race","private_session_id":3099453,"season_name":"Hosted iRacing","season_short_name":"Hosted iRacing","series_name":"Hosted iRacing","series_short_name":"Hosted iRacing","session_name":"Dark Horse DW12 Series","restrict_results":false,"start_time":"2022-10-24T00:00:16Z","track":{"track_id":237,"track_name":"World Wide Technology Raceway (Gateway)","config_name":"Oval"}},"best_lap_num":2,"best_lap_time":242727,"best_nlaps_num":-1,"best_nlaps_time":-1,"best_qual_lap_num":2,"best_qual_lap_time":242727,"best_qual_lap_at":"2022-10-24T00:01:53Z","chunk_info":[{"group_id":430247,"name":"Eric Schaus","cust_id":430247,"display_name":"Eric Schaus","lap_number":0,"flags":3,"incident":false,"session_time":451698,"session_start_time":null,"lap_time":-1,"team_fastest_lap":false,"personal_best_lap":false,"helmet":{"pattern":14,"color1":"13ff00","color2":"111111","color3":"0d00ff","face_type":0,"helmet_type":0},"license_level":0,"car_number":"72","lap_events":["invalid","pitted"],"lap_position":1,"interval":null,"interval_units":null,"fastest_lap":false,"ai":false},{"group_id":457107,"name":"Eric Peterson5","cust_id":457107,"display_name":"Eric Peterson5","lap_number":0,"flags":3,"incident":false,"session_time":662761,"session_start_time":null,"lap_time":-1,"team_fastest_lap":false,"personal_best_lap":false,"helmet":{"pattern":54,"color1":"ccff00","color2":"1903ff","color3":"1903ff","face_type":0,"helmet_type":0},"license_level":0,"car_number":"36","lap_events":["invalid","pitted"],"lap_position":2,"interval":null,"interval_units":null,"fastest_lap":false,"ai":false},{"group_id":430247,"name":"Eric Schaus","cust_id":430247,"display_name":"Eric Schaus","lap_number":1,"flags":0,"incident":false,"session_time":703268,"session_start_time":null,"lap_time":251570,"team_fastest_lap":false,"personal_best_lap":false,"helmet":{"pattern":14,"color1":"13ff00","color2":"111111","color3":"0d00ff","face_type":0,"helmet_type":0},"license_level":0,"car_number":"72","lap_events":[],"lap_position":1,"interval":null,"interval_units":null,"fastest_lap":false,"ai":false},{"group_id":466206,"name":"Gary Corley","cust_id":466206,"display_name":"Gary Corley","lap_number":0,"flags":3,"incident":false,"session_time":733937,"session_start_time":null,"lap_time":-1,"team_fastest_lap":false,"personal_best_lap":false,"helmet":{"pattern":17,"color1":"1210cb","color2":"58dbee","color3":"4d16f3","face_type":0,"helmet_type":0},"license_level":0,"car_number":"7","lap_events":["invalid","pitted"],"lap_position":3,"interval":null,"interval_units":null,"fastest_lap":false,"ai":false},{"group_id":457107,"name":"Eric Peterson5","cust_id":457107,"display_name":"Eric Peterson5","lap_number":1,"flags":0,"incident":false,"session_time":914959,"session_start_time":null,"lap_time":252198,"team_fastest_lap":false,"personal_best_lap":false,"helmet":{"pattern":54,"color1":"ccff00","color2":"1903ff","color3":"1903ff","face_type":0,"helmet_type":0},"license_level":0,"car_number":"36","lap_events":[],"lap_position":2,"interval":-21169,"interval_units":"ms","fastest_lap":false,"ai":false},{"group_id":430247,"name":"Eric Schaus","cust_id":430247,"display_name":"Eric Schaus","lap_number":2,"flags":0,"incident":false,"session_time":945995,"session_start_time":null,"lap_time":242727,"team_fastest_lap":true,"personal_best_lap":true,"helmet":{"pattern":14,"color1":"13ff00","color2":"111111","color3":"0d00ff","face_type":0,"helmet_type":0},"license_level":0,"car_number":"72","lap_events":[],"lap_position":1,"interval":null,"interval_units":null,"fastest_lap":true,"ai":false},{"group_id":466206,"name":"Gary Corley","cust_id":466206,"display_name":"Gary Corley","lap_number":1,"flags":0,"incident":false,"session_time":979748,"session_start_time":null,"lap_time":245811,"team_fastest_lap":false,"personal_best_lap":false,"helmet":{"pattern":17,"color1":"1210cb","color2":"58dbee","color3":"4d16f3","face_type":0,"helmet_type":0},"license_level":0,"car_number":"7","lap_events":[],"lap_position":3,"interval":-1,"interval_units":"lap","fastest_lap":false,"ai":false},{"group_id":457107,"name":"Eric Peterson5","cust_id":457107,"display_name":"Eric Peterson5","lap_number":2,"flags":0,"incident":false,"session_time":1159151,"session_start_time":null,"lap_time":244192,"team_fastest_lap":true,"personal_best_lap":true,"helmet":{"pattern":54,"color1":"ccff00","color2":"1903ff","color3":"1903ff","face_type":0,"helmet_type":0},"license_level":0,"car_number":"36","lap_events":[],"lap_position":2,"interval":-21315,"interval_units":"ms","fastest_lap":false,"ai":false},{"group_id":466206,"name":"Gary Corley","cust_id":466206,"display_name":"Gary Corley","lap_number":2,"flags":0,"incident":false,"session_time":1223138,"session_start_time":null,"lap_time":243390,"team_fastest_lap":true,"personal_best_lap":true,"helmet":{"pattern":17,"color1":"1210cb","color2":"58dbee","color3":"4d16f3","face_type":0,"helmet_type":0},"license_level":0,"car_number":"7","lap_events":[],"lap_position":3,"interval":-27714,"interval_units":"ms","fastest_lap":false,"ai":false},{"group_id":255424,"name":"Craig Forsythe2","cust_id":255424,"display_name":"Craig Forsythe2","lap_number":0,"flags":3,"incident":false,"session_time":1523812,"session_start_time":null,"lap_time":-1,"team_fastest_lap":false,"personal_best_lap":false,"helmet":{"pattern":22,"color1":"ffffff","color2":"00479d","color3":"1a9bff","face_type":0,"helmet_type":0},"license_level":0,"car_number":"27","lap_events":["invalid","pitted"],"lap_position":4,"interval":null,"interval_units":null,"fastest_lap":false,"ai":false},{"group_id":255424,"name":"Craig Forsythe2","cust_id":255424,"display_name":"Craig Forsythe2","lap_number":1,"flags":0,"incident":false,"session_time":1784491,"session_start_time":null,"lap_time":260679,"team_fastest_lap":false,"personal_best_lap":false,"helmet":{"pattern":22,"color1":"ffffff","color2":"00479d","color3":"1a9bff","face_type":0,"helmet_type":0},"license_level":0,"car_number":"27","lap_events":[],"lap_position":4,"interval":-1,"interval_units":"lap","fastest_lap":false,"ai":false},{"group_id":255424,"name":"Craig Forsythe2","cust_id":255424,"display_name":"Craig Forsythe2","lap_number":2,"flags":0,"incident":false,"session_time":2034839,"session_start_time":null,"lap_time":250348,"team_fastest_lap":true,"personal_best_lap":true,"helmet":{"pattern":22,"color1":"ffffff","color2":"00479d","color3":"1a9bff","face_type":0,"helmet_type":0},"license_level":0,"car_number":"27","lap_events":[],"lap_position":4,"interval":-108884,"interval_units":"ms","fastest_lap":false,"ai":false},{"group_id":312578,"name":"Luis Gonzalez Nuñez","cust_id":312578,"display_name":"Luis Gonzalez Nuñez","lap_number":0,"flags":403,"incident":true,"session_time":2292485,"session_start_time":null,"lap_time":-1,"team_fastest_lap":false,"personal_best_lap":false,"helmet":{"pattern":64,"color1":"ffe647","color2":"36d105","color3":"000d70","face_type":0,"helmet_type":0},"license_level":0,"car_number":"14","lap_events":["invalid","pitted","car reset","lost control","discontinuity"],"lap_position":5,"interval":null,"interval_units":null,"fastest_lap":false,"ai":false},{"group_id":507032,"name":"Jeff Hysong","cust_id":507032,"display_name":"Jeff Hysong","lap_number":0,"flags":3,"incident":false,"session_time":2496328,"session_start_time":null,"lap_time":-1,"team_fastest_lap":false,"personal_best_lap":false,"helmet":{"pattern":3,"color1":"001695","color2":"fdfcfc","color3":"fc0706","face_type":0,"helmet_type":0},"license_level":0,"car_number":"18","lap_events":["invalid","pitted"],"lap_position":6,"interval":null,"interval_units":null,"fastest_lap":false,"ai":false},{"group_id":171459,"cust_id":171459,"display_name":"Joe McAdory","lap_number":0,"flags":0,"incident":false,"session_time":2496338,"session_start_time":null,"lap_time":-1,"team_fastest_lap":false,"personal_best_lap":false,"helmet":{"pattern":20,"color1":"000000","color2":"000000","color3":"000000","face_type":0,"helmet_type":0},"license_level":20,"car_number":"312","lap_events":[],"lap_position":0,"interval":null,"interval_units":null,"fastest_lap":false,"ai":false},{"group_id":520552,"cust_id":520552,"display_name":"Joseph Morales","lap_number":0,"flags":0,"incident":false,"session_time":2496348,"session_start_time":null,"lap_time":-1,"team_fastest_lap":false,"personal_best_lap":false,"helmet":{"pattern":19,"color1":"030202","color2":"da0008","color3":"111111","face_type":0,"helmet_type":0},"license_level":19,"car_number":"60","lap_events":[],"lap_position":0,"interval":null,"interval_units":null,"fastest_lap":false,"ai":false},{"group_id":312578,"name":"Luis Gonzalez Nuñez","cust_id":312578,"display_name":"Luis Gonzalez Nuñez","lap_number":1,"flags":0,"incident":false,"session_time":2553450,"session_start_time":null,"lap_time":260965,"team_fastest_lap":false,"personal_best_lap":false,"helmet":{"pattern":64,"color1":"ffe647","color2":"36d105","color3":"000d70","face_type":0,"helmet_type":0},"license_level":0,"car_number":"14","lap_events":[],"lap_position":5,"interval":-1,"interval_units":"lap","fastest_lap":false,"ai":false},{"group_id":507032,"name":"Jeff Hysong","cust_id":507032,"display_name":"Jeff Hysong","lap_number":1,"flags":0,"incident":false,"session_time":2749265,"session_start_time":null,"lap_time":252937,"team_fastest_lap":false,"personal_best_lap":false,"helmet":{"pattern":3,"color1":"001695","color2":"fdfcfc","color3":"fc0706","face_type":0,"helmet_type":0},"license_level":0,"car_number":"18","lap_events":[],"lap_position":6,"interval":-1,"interval_units":"lap","fastest_lap":false,"ai":false},{"group_id":312578,"name":"Luis Gonzalez Nuñez","cust_id":312578,"display_name":"Luis Gonzalez Nuñez","lap_number":2,"flags":0,"incident":false,"session_time":2797097,"session_start_time":null,"lap_time":243647,"team_fastest_lap":true,"personal_best_lap":true,"helmet":{"pattern":64,"color1":"ffe647","color2":"36d105","color3":"000d70","face_type":0,"helmet_type":0},"license_level":0,"car_number":"14","lap_events":[],"lap_position":5,"interval":-185110,"interval_units":"ms","fastest_lap":false,"ai":false},{"group_id":507032,"name":"Jeff Hysong","cust_id":507032,"display_name":"Jeff Hysong","lap_number":2,"flags":0,"incident":false,"session_time":2992354,"session_start_time":null,"lap_time":243089,"team_fastest_lap":true,"personal_best_lap":true,"helmet":{"pattern":3,"color1":"001695","color2":"fdfcfc","color3":"fc0706","face_type":0,"helmet_type":0},"license_level":0,"car_number":"18","lap_events":[],"lap_position":6,"interval":-204635,"interval_units":"ms","fastest_lap":false,"ai":false}]}